{"chrome://messenger/content/messenger.xul":{"mail-toolbar-menubar2":{"autohide":"true"},"qfb-boolean-mode":{"value":"OR"},"messengerWindow":{"screenX":"167","screenY":"27","width":"1024","height":"893","sizemode":"maximized"},"header-view-toolbox":{"mode":"full","iconsize":"small","labelalign":"end"},"header-view-toolbar":{"iconsize":"small"},"attachment-view-toolbox":{"mode":"","iconsize":"","labelalign":""},"attachment-view-toolbar":{"iconsize":""},"locationCol":{"hidden":"true"},"subjectCol":{"sortDirection":"ascending"}},"chrome://messenger/content/messengercompose/messengercompose.xul":{"msgcomposeWindow":{"screenX":"117","screenY":"77","width":"719","height":"359","sizemode":"maximized"}},"about:preferences":{"MailPreferences":{"lastSelected":"paneCompose"}},"chrome://editor/content/EdNamedAnchorProps.xul":{"location":{"offsetX":"767","offsetY":"364"}}}